frappeclient/__init__.py
frappeclient/frappeclient.py
frappeclient/frappeclient_tests.py
frappeclient2-0.1.1.dev0.dist-info/LICENSE.txt
frappeclient2-0.1.1.dev0.dist-info/METADATA
frappeclient2-0.1.1.dev0.dist-info/WHEEL
frappeclient2-0.1.1.dev0.dist-info/top_level.txt
frappeclient2-0.1.1.dev0.dist-info/RECORD
