Metadata-Version: 2.1
Name: frappeclient2
Version: 0.1.1.dev0
Author: Rushabh Mehta
Author-email: rushabh@erpnext.com
License-File: LICENSE.txt
Requires-Dist: requests>=2.3.0
Requires-Dist: ipython
